{
    "agent_cfg":{
        "algorithm_cfg":{
            "name":"reinforce",
            "var_schedule_cfg":null,
            "gamma":0.99,
            "rets_mean_baseline":true,
            "policy_loss_var":1,
            "entropy_reg_var_cfg":{
                "name":"linear",
                "var_start":0.01,
                "var_end":0.005,
                "star_epoch":0,
                "end_epoch":50000
            },
            "batch_learn_times_per_train":4
        },
        "net_cfg":{
            "name":"MLPNet",
            "hid_layers":[32, 16],
            "hid_layers_activation":"Selu"
        },
        "optimizer_cfg":{
            "name":"Adam",
            "lr":1e-4,
            "weight_decay": 1e-08,
            "betas": [
                0.9,
                0.999
            ]
        },
        "lr_schedule_cfg":null,
        "memory_cfg":{
            "name":"OnPolicyBatch"
        },
        "train_exp_size":512,
        "max_epoch":100000
    },
    "env":{
        "name":"CartPole",
        "solved_total_reward":99900,
        "finish_total_reward":100000,
        "survival_T":100000
    },
    "model_path":null,
    "valid":{
        "valid_step":100,
        "valid_times":5,
        "not_improve_finish_step":5
    }
}